securepack/__init__.py
securepack/securepack.py
securepack-0.0.5.dist-info/LICENSE.md
securepack-0.0.5.dist-info/METADATA
securepack-0.0.5.dist-info/WHEEL
securepack-0.0.5.dist-info/entry_points.txt
securepack-0.0.5.dist-info/top_level.txt
securepack-0.0.5.dist-info/RECORD
