Metadata-Version: 2.1
Name: securepack
Version: 0.0.5
Summary: Securepack helps securing packages from typosquatting attack
Home-page: https://github.com/Ruturaj4/securepack
Author: Ruturaj Kiran Vaidya
Author-email: ruturajkvaidya@gmail.com
License: UNKNOWN
Platform: UNKNOWN
Classifier: Programming Language :: Python :: 3
Classifier: License :: OSI Approved :: MIT License
Classifier: Operating System :: OS Independent
Requires-Dist: fuzzyset
Requires-Dist: python-levenshtein
Requires-Dist: texttable
